cerberuspy
